anchovy/__init__.py
anchovy/__main__.py
anchovy/cli.py
anchovy/core.py
anchovy/css.py
anchovy/custody.py
anchovy/dependencies.py
anchovy/images.py
anchovy/include.py
anchovy/jinja.py
anchovy/minify.py
anchovy/paths.py
anchovy/pretty_utils.py
anchovy/server.py
anchovy/simple.py
anchovy/test_harness.py
anchovy/components/__init__.py
anchovy/components/md_frontmatter.py
anchovy/components/md_rendering.py
anchovy-1.0.1.dist-info/LICENSE
anchovy-1.0.1.dist-info/METADATA
anchovy-1.0.1.dist-info/WHEEL
anchovy-1.0.1.dist-info/entry_points.txt
anchovy-1.0.1.dist-info/top_level.txt
anchovy-1.0.1.dist-info/RECORD
