Metadata-Version: 2.1
Name: anchovy
Version: 1.0.1
Summary: A minimal, unopinionated file processing engine intended for static website generation.
Author-email: Daniel Foerster <pydsigner@gmail.com>
License: Apache-2.0
Project-URL: Source, https://github.com/pydsigner/anchovy
Keywords: static,website,generation,html,css,template
Classifier: Development Status :: 4 - Beta
Classifier: Intended Audience :: Developers
Classifier: License :: OSI Approved :: Apache Software License
Classifier: Operating System :: OS Independent
Classifier: Programming Language :: Python :: 3
Classifier: Programming Language :: Python :: 3 :: Only
Classifier: Programming Language :: Python :: 3.10
Classifier: Programming Language :: Python :: 3.11
Classifier: Programming Language :: Python :: 3.12
Classifier: Topic :: Internet :: WWW/HTTP
Classifier: Topic :: Software Development :: Pre-processors
Classifier: Topic :: Text Processing :: Markup
Classifier: Typing :: Typed
Requires-Python: >=3.10
License-File: LICENSE
Provides-Extra: all
Requires-Dist: anchovy[base] ; extra == 'all'
Provides-Extra: base
Requires-Dist: anchovy[web] ; extra == 'base'
Requires-Dist: anchovy[include] ; extra == 'base'
Requires-Dist: anchovy[pretty] ; extra == 'base'
Provides-Extra: cq
Requires-Dist: anchovy[all] ; extra == 'cq'
Requires-Dist: tqdm >=4.65.0 ; extra == 'cq'
Requires-Dist: minify-html >=0.11.1 ; extra == 'cq'
Requires-Dist: pylint ; extra == 'cq'
Requires-Dist: pyright ; extra == 'cq'
Requires-Dist: pytest ; extra == 'cq'
Requires-Dist: pytest-cov ; extra == 'cq'
Provides-Extra: css
Requires-Dist: anchovy-css >=0.1.1 ; extra == 'css'
Provides-Extra: include
Requires-Dist: requests >=2.31.0 ; extra == 'include'
Requires-Dist: anchovy[toml] ; extra == 'include'
Provides-Extra: jinja
Requires-Dist: Jinja2 >=3.1.2 ; extra == 'jinja'
Provides-Extra: markdown
Requires-Dist: anchovy[jinja] ; extra == 'markdown'
Requires-Dist: anchovy[toml] ; extra == 'markdown'
Requires-Dist: anchovy[yaml] ; extra == 'markdown'
Requires-Dist: markdown-it-py >=3.0.0 ; extra == 'markdown'
Requires-Dist: mdit-py-plugins >=0.4.0 ; extra == 'markdown'
Requires-Dist: Pygments >=2.12.0 ; extra == 'markdown'
Provides-Extra: minify
Requires-Dist: lightningcss <1.0,>=0.1.1 ; extra == 'minify'
Requires-Dist: minify-html-onepass >=0.11.1 ; extra == 'minify'
Requires-Dist: tdewolff-minify >=2.20.6 ; (sys_platform != "darwin") and extra == 'minify'
Provides-Extra: pillow
Requires-Dist: Pillow >=9.2.0 ; extra == 'pillow'
Provides-Extra: pretty
Requires-Dist: rich >=12.5.1 ; extra == 'pretty'
Provides-Extra: toml
Requires-Dist: tomli >=2.0.1 ; (python_version < "3.11") and extra == 'toml'
Provides-Extra: web
Requires-Dist: anchovy[markdown] ; extra == 'web'
Requires-Dist: anchovy[css] ; extra == 'web'
Requires-Dist: anchovy[pillow] ; extra == 'web'
Requires-Dist: anchovy[minify] ; extra == 'web'
Provides-Extra: yaml
Requires-Dist: ruamel.yaml >=0.18.5 ; extra == 'yaml'
